panasoniceolia/__init__.py
panasoniceolia/__main__.py
panasoniceolia/constants.py
panasoniceolia/session.py
panasoniceolia/urls.py
panasoniceolia-0.0.8.dist-info/LICENSE
panasoniceolia-0.0.8.dist-info/METADATA
panasoniceolia-0.0.8.dist-info/WHEEL
panasoniceolia-0.0.8.dist-info/entry_points.txt
panasoniceolia-0.0.8.dist-info/top_level.txt
panasoniceolia-0.0.8.dist-info/RECORD
