Metadata-Version: 2.1
Name: panasoniceolia
Version: 0.0.8
Summary: Read and change status of Panasonic Eolia devices
Home-page: https://github.com/avolmensky/python-panasonic-eolia
Author: avolmensky
License: MIT
Keywords: home automation panasonic eolia climate
Platform: UNKNOWN
Classifier: Topic :: Home Automation
Classifier: License :: OSI Approved :: MIT License
Classifier: Programming Language :: Python :: 3.10
License-File: LICENSE
Requires-Dist: requests (>=2.20.0)
